enumb/__init__.py
enumb/bases.py
enumb/enums.py
enumb/generators.py
enumb/meta.py
enumb/models.py
enumb/types.py
enumb/utils.py
enumb-0.1.4.dist-info/LICENSE
enumb-0.1.4.dist-info/WHEEL
enumb-0.1.4.dist-info/METADATA
enumb-0.1.4.dist-info/RECORD
