Metadata-Version: 2.1
Name: enumb
Version: 0.1.4
Summary: Concise, Pythonic Enums
Author: Tom Bulled
Author-email: 26026015+tombulled@users.noreply.github.com
Requires-Python: >=3.8,<4.0
Classifier: Programming Language :: Python :: 3
Classifier: Programming Language :: Python :: 3.8
Classifier: Programming Language :: Python :: 3.9
Requires-Dist: cassidy (>=0.1.2,<0.2.0)
Requires-Dist: expo (>=0.1.1,<0.2.0)
